jupiter_python_sdk_public/__init__.py
jupiter_python_sdk_public/jupiter.py
jupiter_python_sdk_public-0.0.2.2.dist-info/LICENSE.txt
jupiter_python_sdk_public-0.0.2.2.dist-info/METADATA
jupiter_python_sdk_public-0.0.2.2.dist-info/WHEEL
jupiter_python_sdk_public-0.0.2.2.dist-info/top_level.txt
jupiter_python_sdk_public-0.0.2.2.dist-info/RECORD
