Metadata-Version: 2.2
Name: jupiter-python-sdk-public
Version: 0.0.2.2
Summary: Jupiter Python SDK
Author: Samuel Sallee
Author-email: sam@tenxor.sh
License: LICENSE.txt
Keywords: python,solana,jupiter,dex,trading,sdk
Classifier: Development Status :: 3 - Alpha
Classifier: Intended Audience :: Developers
Classifier: Programming Language :: Python :: 3
Classifier: Operating System :: Unix
Classifier: Operating System :: MacOS :: MacOS X
Classifier: Operating System :: Microsoft :: Windows
License-File: LICENSE.txt
Requires-Dist: base58
Requires-Dist: solders
Requires-Dist: solana
Requires-Dist: httpx
Requires-Dist: anchorpy
Dynamic: author
Dynamic: author-email
Dynamic: classifier
Dynamic: description
Dynamic: description-content-type
Dynamic: keywords
Dynamic: license
Dynamic: requires-dist
Dynamic: summary
